django_otp_provider/__init__.py
django_otp_provider/conf.py
django_otp_provider/models.py
django_otp_provider/selectors.py
django_otp_provider/services.py
django_otp_provider/tasks.py
django_otp_provider/utils.py
tests/__init__.py
tests/services/__init__.py
tests/services/test_generate_otp.py
tests/services/test_verify_otp.py
django_otp_provider-1.0.2.dist-info/LICENSE.txt
django_otp_provider-1.0.2.dist-info/METADATA
django_otp_provider-1.0.2.dist-info/WHEEL
django_otp_provider-1.0.2.dist-info/top_level.txt
django_otp_provider-1.0.2.dist-info/RECORD
