Metadata-Version: 2.1
Name: django-otp-provider
Version: 1.0.2
Summary: Django OTP (One Time Password)
Home-page: https://github.com/a1k89/django_otp_provider
Author: Andrei Koptev
Author-email: akoptev1989@ya.ru
License: MIT
Keywords: django otp
Platform: UNKNOWN
Classifier: Framework :: Django
Classifier: Intended Audience :: Developers
Classifier: Intended Audience :: System Administrators
Classifier: Operating System :: OS Independent
Classifier: Topic :: Software Development
Requires-Dist: Django (>=2.0)
Requires-Dist: celery (>=5.0)
Requires-Dist: pyjwt
